sihdata/__init__.py
sihdata/sihdata.py
sihscraper/__init__.py
sihscraper/sihscraper.py
sihscraper/tests/__init__.py
sihscraper/tests/test_sihscraper.py
sihtools/__init__.py
sihtools/sihtools.py
sihtools/tests/__init__.py
sihtools/tests/test_sihtools.py
sih_ingestor_packages-1.2.8.dist-info/LICENSE
sih_ingestor_packages-1.2.8.dist-info/METADATA
sih_ingestor_packages-1.2.8.dist-info/WHEEL
sih_ingestor_packages-1.2.8.dist-info/top_level.txt
sih_ingestor_packages-1.2.8.dist-info/RECORD
